{
  "AddToPlayList": "Add To Play List",
  "CommentsCount": "",
  "Country": "Іспанія",
  "Countries": [ "Іспанія" ],
  "Description": "Декілька людей прокидається в якійсь багатоповерховій підземній в'язниці, в яку вони потрапили добровільно. На кожному рівні перебувають двоє ув'язнених, а скільки всього рівнів – невідомо. Всі поверхи пов'язує між собою спільну криницю, через яку щодня опускається платформа з їжею. На ній - неймовірна кількість страв, але чим нижче живуть ув'язнені, тим менше шансів, що вони щось отримають.",
  "Duration": "98 хв/01:38",
  "Genre": "Films",
  "IMDB": "7.00",
  "Name": "Платформа",
  "Picture": "El hoyo.jpg",
  "Quality": "BDRip",
  "Rating": "7.126",
  "RecommendAge": "16+",
  "Translation": "Професійний (багатоголосий)",
  "Type": "films",
  "Video": "ThePlatform.mp4",
  "Views": 43,
  "ViewUsers": "View Users",
  "Year": 2019,
  "Actors": [
    {
      "Name": "Іван Массаге",
      "Role": "Горенг"
    },
    {
      "Name": "Антонія Сан Хуан",
      "Role": "Имогири"
    }
  ],
  "Series": [
    "ThePlatform.mp4"
  ]
}